{
	"journey": {
		"type": "journey",
		"legs": [
			{
				"departure": "2024-01-31T23:50:00+01:00",
				"plannedDeparture": "2024-01-31T23:50:00+01:00",
				"departureDelay": null,
				"arrival": "2024-02-01T00:06:00+01:00",
				"plannedArrival": "2024-02-01T00:06:00+01:00",
				"arrivalDelay": null,
				"public": true,
				"walking": true,
				"distance": 1246
			},
			{
				"departure": "2024-02-01T00:06:00+01:00",
				"plannedDeparture": "2024-02-01T00:06:00+01:00",
				"departureDelay": null,
				"arrival": "2024-02-01T00:08:00+01:00",
				"plannedArrival": "2024-02-01T00:08:00+01:00",
				"arrivalDelay": null,
				"reachable": true,
				"tripId": "1|1055956|0|80|31012024",
				"line": {
					"name": "Bus 848"
				}
			},
			{
				"departure": "2024-02-01T00:08:00+01:00",
				"plannedDeparture": "2024-02-01T00:08:00+01:00",
				"departureDelay": null,
				"arrival": "2024-02-01T00:12:00+01:00",
				"plannedArrival": "2024-02-01T00:12:00+01:00",
				"arrivalDelay": null,
				"public": true,
				"walking": true,
				"distance": 665
			},
			{
				"departure": "2024-02-01T00:12:00+01:00",
				"plannedDeparture": "2024-02-01T00:12:00+01:00",
				"departureDelay": 0,
				"arrival": "2024-02-01T00:28:00+01:00",
				"plannedArrival": "2024-02-01T00:28:00+01:00",
				"arrivalDelay": 0,
				"reachable": true,
				"tripId": "1|202123|0|80|31012024",
				"line": {
					"name": "S 8"
				}
			}
		],
		"refreshToken": "G@F$A=2@O=51.19 , 6.68@X=6680000@Y=51190000@a=128@$A=1@O=Neustr., Neuss@L=586641@a=128@$202401312350$202402010006$$$1$$$$$$§T$A=1@O=Neustr., Neuss@L=586641@a=128@$A=1@O=Hauptbahnhof, Neuss@L=374055@a=128@$202402010006$202402010008$Bus  848$$1$$$$$$§W$A=1@O=Hauptbahnhof, Neuss@L=374055@a=128@$A=1@O=Neuss Hbf@L=8000274@a=128@$202402010008$202402010012$$$1$$$$$$§T$A=1@O=Neuss Hbf@L=8000274@a=128@$A=1@O=Düsseldorf Hbf@L=8000085@a=128@$202402010012$202402010028$S      8$$1$$$$$$",
		"price": null
	},
	"realtimeDataUpdatedAt": 1706741949
}
